{"drawId":2020085,"drawDate":"2020-02-21T19:00:00","week":8,"year":2020,"draws":[[47,39,45,13,2],[4,6]],"addonDraw":[5,4,2,0,8,7],"drawWinnings":[[{"amount":0,"wins":0},{"amount":24337542,"wins":0},{"amount":2863240,"wins":0},{"amount":127254,"wins":2},{"amount":6615,"wins":29},{"amount":3027,"wins":41},{"amount":1453,"wins":64},{"amount":513,"wins":884},{"amount":498,"wins":929},{"amount":398,"wins":1748},{"amount":235,"wins":4907},{"amount":210,"wins":13999}]],"addonWinnings":[{"amount":0,"wins":0},{"amount":200000,"wins":1},{"amount":20000,"wins":12},{"amount":2000,"wins":107},{"amount":200,"wins":1076},{"amount":120,"wins":10965}],"winsByCountry":["","Švédsko 1x, Polsko 1x","Finsko 2x, Slovensko 1x, Itálie 1x, Německo 2x"],"specialPrizes":[{"name":"Český pátek","count":0,"type":"NFP","prizes":[]}]}