{"drawId":2021255,"drawDate":"2021-06-25T19:00:00","week":25,"year":2021,"draws":[[30,4,22,47,17],[1,8]],"addonDraw":[4,0,6,9,4,3],"drawWinnings":[[{"amount":1228250489,"wins":0},{"amount":8126623,"wins":0},{"amount":1338500,"wins":0},{"amount":104570,"wins":3},{"amount":5767,"wins":20},{"amount":2209,"wins":43},{"amount":1592,"wins":56},{"amount":586,"wins":946},{"amount":463,"wins":1044},{"amount":349,"wins":2003},{"amount":277,"wins":4880},{"amount":208,"wins":15246}]],"addonWinnings":[{"amount":0,"wins":0},{"amount":200000,"wins":1},{"amount":20000,"wins":11},{"amount":2000,"wins":127},{"amount":200,"wins":1140},{"amount":120,"wins":11076}],"winsByCountry":["Německo 1x","Finsko 1x, Německo 5x, Norsko 1x","Finsko 1x, Maďarsko 1x, Německo 9x, Norsko 2x, Chorvatsko 1x, Dánsko 1x"],"specialPrizes":[]}