{"drawId":2022242,"drawDate":"2022-06-14T19:00:00","week":24,"year":2022,"draws":[[28,30,35,11,50],[7,8]],"addonDraw":[0,1,8,0,5,0],"drawWinnings":[[{"amount":0,"wins":0},{"amount":20496714,"wins":0},{"amount":11559192,"wins":0},{"amount":136189,"wins":0},{"amount":9026,"wins":4},{"amount":4120,"wins":17},{"amount":3568,"wins":16},{"amount":628,"wins":220},{"amount":504,"wins":298},{"amount":485,"wins":582},{"amount":301,"wins":1158},{"amount":235,"wins":4386}]],"addonWinnings":[{"amount":0,"wins":0},{"amount":200000,"wins":1},{"amount":20000,"wins":5},{"amount":2000,"wins":27},{"amount":200,"wins":333},{"amount":120,"wins":3600}],"winsByCountry":["","Německo 1x","Španělsko 1x"],"specialPrizes":[]}