{"drawId":2023455,"drawDate":"2023-11-10T19:00:00","week":45,"year":2023,"draws":[[29,17,1,22,31],[5,6]],"addonDraw":[7,0,7,9,7,2],"drawWinnings":[[{"amount":0,"wins":0},{"amount":6839390,"wins":0},{"amount":3857097,"wins":0},{"amount":159054,"wins":0},{"amount":7621,"wins":9},{"amount":3632,"wins":24},{"amount":2946,"wins":21},{"amount":576,"wins":332},{"amount":463,"wins":525},{"amount":429,"wins":1167},{"amount":296,"wins":1764},{"amount":228,"wins":7462}]],"addonWinnings":[{"amount":0,"wins":0},{"amount":0,"wins":0},{"amount":20000,"wins":9},{"amount":2000,"wins":79},{"amount":200,"wins":629},{"amount":120,"wins":6116}],"winsByCountry":["","Německo 3x, Slovinsko 1x, Švédsko 1x, Finsko 1x","Německo 5x, Švédsko 1x"],"specialPrizes":[]}