{"drawId":2024012,"drawDate":"2024-01-02T19:00:00","week":1,"year":2024,"draws":[[48,19,26,49,36],[11,10]],"addonDraw":[3,2,8,4,4,5],"drawWinnings":[[{"amount":0,"wins":0},{"amount":20575596,"wins":0},{"amount":4351377,"wins":1},{"amount":151104,"wins":0},{"amount":9061,"wins":14},{"amount":5156,"wins":36},{"amount":3070,"wins":34},{"amount":824,"wins":436},{"amount":567,"wins":762},{"amount":429,"wins":1872},{"amount":414,"wins":2668},{"amount":274,"wins":10712}]],"addonWinnings":[{"amount":0,"wins":0},{"amount":0,"wins":0},{"amount":20000,"wins":8},{"amount":2000,"wins":81},{"amount":200,"wins":921},{"amount":120,"wins":9220}],"winsByCountry":["","Německo 2x, Polsko 1x","Německo 5x, Španělsko 1x, Česká republika 1x, Finsko 1x"],"specialPrizes":[]}