{"drawId":2024082,"drawDate":"2024-02-20T19:00:00","week":8,"year":2024,"draws":[[15,1,30,3,11],[4,10]],"addonDraw":[4,6,8,6,6,2],"drawWinnings":[[{"amount":0,"wins":0},{"amount":9934656,"wins":0},{"amount":2401149,"wins":0},{"amount":126019,"wins":0},{"amount":6780,"wins":15},{"amount":3724,"wins":16},{"amount":2153,"wins":19},{"amount":653,"wins":241},{"amount":480,"wins":357},{"amount":373,"wins":888},{"amount":333,"wins":1272},{"amount":249,"wins":5011}]],"addonWinnings":[{"amount":0,"wins":0},{"amount":200000,"wins":1},{"amount":20000,"wins":5},{"amount":2000,"wins":54},{"amount":200,"wins":431},{"amount":120,"wins":4337}],"winsByCountry":["","Německo 1x, Dánsko 1x, Finsko 1x","Německo 4x, Španělsko 2x, Polsko 1x"],"specialPrizes":[]}