{"drawId":2024462,"drawDate":"2024-11-12T19:00:00","week":46,"year":2024,"draws":[[2,49,38,3,34],[10,11]],"addonDraw":[0,6,5,5,8,0],"drawWinnings":[[{"amount":0,"wins":0},{"amount":22254859,"wins":0},{"amount":4183567,"wins":0},{"amount":155265,"wins":1},{"amount":9738,"wins":14},{"amount":5205,"wins":18},{"amount":3446,"wins":35},{"amount":822,"wins":553},{"amount":594,"wins":713},{"amount":464,"wins":1658},{"amount":406,"wins":2772},{"amount":279,"wins":11049}]],"addonWinnings":[{"amount":0,"wins":0},{"amount":100000,"wins":1},{"amount":10000,"wins":8},{"amount":1000,"wins":76},{"amount":100,"wins":820},{"amount":60,"wins":9138},{"amount":60,"wins":21238}],"winsByCountry":["","Norsko 1x, Německo 1x, Slovensko 1x","Německo 4x, Nizozemsko 1x, Polsko 2x, Finsko 2x"],"specialPrizes":[]}