{"drawId":2025045,"drawDate":"2025-01-24T19:00:00","week":4,"year":2025,"draws":[[46,16,2,9,47],[9,3]],"addonDraw":[7,1,5,1,1,9],"drawWinnings":[[{"amount":0,"wins":0},{"amount":16714472,"wins":0},{"amount":3142059,"wins":0},{"amount":99243,"wins":1},{"amount":8780,"wins":17},{"amount":3540,"wins":48},{"amount":3540,"wins":20},{"amount":521,"wins":661},{"amount":521,"wins":749},{"amount":491,"wins":1589},{"amount":243,"wins":3730},{"amount":243,"wins":11718}]],"addonWinnings":[{"amount":0,"wins":0},{"amount":0,"wins":0},{"amount":10000,"wins":11},{"amount":1000,"wins":79},{"amount":100,"wins":940},{"amount":60,"wins":9220},{"amount":60,"wins":20366}],"winsByCountry":["","Německo 1x, Itálie 1x, Finsko 1x","Německo 4x, Dánsko 3x, Itálie 1x, Švédsko 1x"],"specialPrizes":[{"name":"3x zlatá cihla","count":0,"type":"NFP","prizes":[]}]}